[
  {
    "parts": [
      {
        "name": "Trunk/boot/hatch",
        "price": 2200.99
      },
      {
        "name": "Piston",
        "price": 94.99
      },
      {
        "name": "Front Right Side Door Glass",
        "price": 100.91
      }
    ],
    "make": "Opel",
    "model": "Omega",
    "travelledDistance": 2147483647
  },
  {
    "parts": [
      {
        "name": "Door control module",
        "price": 421.99
      },
      {
        "name": "Rear Right Side Inner door handle",
        "price": 79.99
      },
      {
        "name": "Front Left Side Outer door handle",
        "price": 999.99
      },
      {
        "name": "Water tank",
        "price": 100.99
      }
    ],
    "make": "Opel",
    "model": "Astra",
    "travelledDistance": 9223372036854775807
  },
  {
    "parts": [
      {
        "name": "Engine cradle",
        "price": 39.99
      },
      {
        "name": "Rocker",
        "price": 100.99
      },
      {
        "name": "Radiator gasket",
        "price": 140.99
      }
    ],
    "make": "Opel",
    "model": "Astra",
    "travelledDistance": 922337203685807
  },
  {
    "parts": [
      {
        "name": "Fuel tank",
        "price": 100.98
      },
      {
        "name": "Fan blade",
        "price": 150.99
      },
      {
        "name": "Distributor cap",
        "price": 9.99
      },
      {
        "name": "Drive belt",
        "price": 3.99
      }
    ],
    "make": "Opel",
    "model": "Corsa",
    "travelledDistance": 214747
  },
  {
    "parts": [
      {
        "name": "Front Right Side Door Glass",
        "price": 100.91
      },
      {
        "name": "Cylinder head",
        "price": 6.99
      },
      {
        "name": "Fascia",
        "price": 100.34
      },
      {
        "name": "Drive belt",
        "price": 3.99
      }
    ],
    "make": "Opel",
    "model": "Kadet",
    "travelledDistance": 21474847
  },
  {
    "parts": [
      {
        "name": "Thermostat",
        "price": 1050.99
      },
      {
        "name": "Rear Right Side Door Glass",
        "price": 100.90
      },
      {
        "name": "Radiator (fan) shroud",
        "price": 300.99
      }
    ],
    "make": "Opel",
    "model": "Vectra",
    "travelledDistance": 9223372854775807
  },
  {
    "parts": [
      {
        "name": "Radiator ",
        "price": 100.99
      },
      {
        "name": "Rear Right Side Inner door handle",
        "price": 79.99
      },
      {
        "name": "Back Door Outer Door Handle",
        "price": 43.99
      }
    ],
    "make": "Opel",
    "model": "Insignia",
    "travelledDistance": 2147483647
  },
  {
    "parts": [
      {
        "name": "Engine valve",
        "price": 49.99
      },
      {
        "name": "Front Left Side Inner door handle",
        "price": 77.99
      },
      {
        "name": "Exhaust clamp and bracket",
        "price": 140.99
      }
    ],
    "make": "Opel",
    "model": "Astra",
    "travelledDistance": 922336854775807
  },
  {
    "parts": [
      {
        "name": "Timing tape",
        "price": 40.90
      },
      {
        "name": "Sunroof Rail",
        "price": 100.25
      },
      {
        "name": "Rear Left Quarter Glass",
        "price": 100.55
      }
    ],
    "make": "Opel",
    "model": "Corsa",
    "travelledDistance": 21474847
  },
  {
    "parts": [
      {
        "name": "Fuel tank",
        "price": 100.98
      },
      {
        "name": "Rear Left Side Inner door handle",
        "price": 93.99
      },
      {
        "name": "Oil pan",
        "price": 140.99
      },
      {
        "name": "Transmission gear",
        "price": 15.99
      }
    ],
    "make": "Opel",
    "model": "Omega",
    "travelledDistance": 2147483647
  },
  {
    "parts": [
      {
        "name": "Valance",
        "price": 1002.99
      },
      {
        "name": "Window regulator",
        "price": 100.99
      },
      {
        "name": "Welded assembly",
        "price": 1020.99
      }
    ],
    "make": "Opel",
    "model": "Insignia",
    "travelledDistance": 9223372036854775807
  },
  {
    "parts": [
      {
        "name": "Window motor",
        "price": 123.49
      },
      {
        "name": "Air filter",
        "price": 200.99
      },
      {
        "name": "Decklid",
        "price": 1060.34
      },
      {
        "name": "Front fascia",
        "price": 11.99
      }
    ],
    "make": "Opel",
    "model": "Vectra",
    "travelledDistance": 2147483647
  },
  {
    "parts": [
      {
        "name": "Poppet valve",
        "price": 88.99
      },
      {
        "name": "Fender",
        "price": 10.34
      },
      {
        "name": "Camshaft",
        "price": 100.98
      }
    ],
    "make": "Opel",
    "model": "Astra",
    "travelledDistance": 2147483647
  },
  {
    "parts": [
      {
        "name": "Rear Left Side Window motor",
        "price": 144.99
      },
      {
        "name": "Water pump pulley",
        "price": 150.99
      },
      {
        "name": "Rear Right Side Outer door handle",
        "price": 80.99
      }
    ],
    "make": "Opel",
    "model": "Omega",
    "travelledDistance": 2147483647
  },
  {
    "parts": [
      {
        "name": "Back Door Outer Door Handle",
        "price": 43.99
      },
      {
        "name": "Oil strainer",
        "price": 45.29
      },
      {
        "name": "Pillar",
        "price": 100.99
      },
      {
        "name": "Rear Right Side Door Glass",
        "price": 100.90
      }
    ],
    "make": "Opel",
    "model": "Corsa",
    "travelledDistance": 2147483647
  },
  {
    "parts": [
      {
        "name": "Engine cradle",
        "price": 39.99
      },
      {
        "name": "Center-locking",
        "price": 313.99
      },
      {
        "name": "Oil strainer",
        "price": 45.29
      }
    ],
    "make": "Opel",
    "model": "Insignia",
    "travelledDistance": 9223372036854775807
  },
  {
    "parts": [
      {
        "name": "Radiator pressure cap",
        "price": 600.99
      },
      {
        "name": "Rocker cover",
        "price": 10.99
      },
      {
        "name": "Fuel rail",
        "price": 107.99
      }
    ],
    "make": "Opel",
    "model": "Omega",
    "travelledDistance": 9223336854775807
  },
  {
    "parts": [
      {
        "name": "Tappet",
        "price": 300.29
      },
      {
        "name": "Fuel pressure regulator",
        "price": 100.99
      },
      {
        "name": "Steering arm",
        "price": 104.99
      }
    ],
    "make": "Opel",
    "model": "Corsa",
    "travelledDistance": 2
  },
  {
    "parts": [
      {
        "name": "Harmonic balancer",
        "price": 67.99
      },
      {
        "name": "Differential seal",
        "price": 109.99
      },
      {
        "name": "Timing tape",
        "price": 40.90
      }
    ],
    "make": "Opel",
    "model": "Omega",
    "travelledDistance": 1
  },
  {
    "parts": [
      {
        "name": "Decklid",
        "price": 1060.34
      },
      {
        "name": "Oil filter",
        "price": 200.99
      },
      {
        "name": "Water tank",
        "price": 100.99
      },
      {
        "name": "Rear Left Side Door Glass",
        "price": 100.66
      }
    ],
    "make": "BMW",
    "model": "F20",
    "travelledDistance": 2147483647
  },
  {
    "parts": [
      {
        "name": "Oil gasket",
        "price": 130.99
      },
      {
        "name": "Steering arm",
        "price": 104.99
      },
      {
        "name": "Fascia",
        "price": 100.34
      }
    ],
    "make": "BMW",
    "model": "F25",
    "travelledDistance": 9223372036854775807
  },
  {
    "parts": [
      {
        "name": "Rear Right Side Inner door handle",
        "price": 79.99
      },
      {
        "name": "Turbocharger",
        "price": 0.40
      },
      {
        "name": "Water neck o-ring",
        "price": 43.99
      },
      {
        "name": "Distributor cap",
        "price": 9.99
      }
    ],
    "make": "BMW",
    "model": "M5 F10",
    "travelledDistance": 10
  },
  {
    "parts": [
      {
        "name": "Starter motor",
        "price": 0.99
      },
      {
        "name": "Water tank",
        "price": 100.99
      },
      {
        "name": "Door water-shield",
        "price": 123.99
      }
    ],
    "make": "BMW",
    "model": "F04",
    "travelledDistance": 100000
  },
  {
    "parts": [
      {
        "name": "Radiator bolt",
        "price": 160.99
      },
      {
        "name": "Water neck o-ring",
        "price": 43.99
      },
      {
        "name": "Fan blade",
        "price": 150.99
      },
      {
        "name": "Oil pipe",
        "price": 100.29
      }
    ],
    "make": "BMW",
    "model": "E88",
    "travelledDistance": 200000
  },
  {
    "parts": [
      {
        "name": "Sunroof Glass",
        "price": 205.24
      },
      {
        "name": "Fascia",
        "price": 100.34
      },
      {
        "name": "Front Right Outer door handle",
        "price": 999.99
      }
    ],
    "make": "BMW",
    "model": "M Roadster E85",
    "travelledDistance": 92233720365807
  },
  {
    "parts": [
      {
        "name": "Cowl screen",
        "price": 1500.34
      },
      {
        "name": "Back Door Outer Door Handle",
        "price": 43.99
      },
      {
        "name": "Rear Right Quarter Glass",
        "price": 100.66
      },
      {
        "name": "Water neck",
        "price": 900.99
      }
    ],
    "make": "BMW",
    "model": "1M Coupe",
    "travelledDistance": 2147
  },
  {
    "parts": [
      {
        "name": "Back Door Outer Door Handle",
        "price": 43.99
      },
      {
        "name": "Rear Right Quarter Glass",
        "price": 100.66
      },
      {
        "name": "Water neck",
        "price": 900.99
      }
    ],
    "make": "BMW",
    "model": "X6 M",
    "travelledDistance": 922775807
  },
  {
    "parts": [
      {
        "name": "Trunk/boot/hatch",
        "price": 2200.99
      },
      {
        "name": "Crank pulley",
        "price": 2.80
      },
      {
        "name": "Fuel rail",
        "price": 107.99
      },
      {
        "name": "Rear Right Side Inner door handle",
        "price": 79.99
      }
    ],
    "make": "BMW",
    "model": "E67",
    "travelledDistance": 21447
  },
  {
    "parts": [
      {
        "name": "Door latch",
        "price": 2331.99
      },
      {
        "name": "Fan clutch",
        "price": 120.99
      },
      {
        "name": "Fan blade",
        "price": 150.99
      }
    ],
    "make": "BMW",
    "model": "M6 E63",
    "travelledDistance": 92235807
  },
  {
    "parts": [
      {
        "name": "Hinge",
        "price": 11.99
      },
      {
        "name": "Fuel pressure regulator",
        "price": 100.99
      },
      {
        "name": "Valve cover",
        "price": 130.99
      }
    ],
    "make": "BMW",
    "model": "M6 E63",
    "travelledDistance": 2147
  },
  {
    "parts": [
      {
        "name": "Trim package",
        "price": 1900.99
      },
      {
        "name": "Decklid",
        "price": 1060.34
      },
      {
        "name": "Choke cable",
        "price": 130.99
      }
    ],
    "make": "BMW",
    "model": "F20",
    "travelledDistance": 21447
  },
  {
    "parts": [
      {
        "name": "Trunk/boot/hatch",
        "price": 2200.99
      },
      {
        "name": "Rocker cover",
        "price": 10.99
      },
      {
        "name": "Heat shield",
        "price": 10.99
      },
      {
        "name": "Engine",
        "price": 100.99
      }
    ],
    "make": "BMW",
    "model": "F04",
    "travelledDistance": 2143647
  },
  {
    "parts": [
      {
        "name": "Fuel tank",
        "price": 100.98
      },
      {
        "name": "Valve stem seal",
        "price": 120.99
      },
      {
        "name": "Steering arm",
        "price": 104.99
      }
    ],
    "make": "BMW",
    "model": "M5 F10",
    "travelledDistance": 27483647
  },
  {
    "parts": [
      {
        "name": "Valve housing",
        "price": 400.99
      },
      {
        "name": "Valve stem seal",
        "price": 120.99
      },
      {
        "name": "Front fascia",
        "price": 11.99
      }
    ],
    "make": "BMW",
    "model": "X6 M",
    "travelledDistance": 2036854775807
  },
  {
    "parts": [
      {
        "name": "Quarter panel",
        "price": 100.99
      },
      {
        "name": "Timing tape",
        "price": 40.90
      },
      {
        "name": "Front clip",
        "price": 100.00
      }
    ],
    "make": "BMW",
    "model": "F20",
    "travelledDistance": 83647
  },
  {
    "parts": [
      {
        "name": "Sunroof Glass",
        "price": 205.24
      },
      {
        "name": "Rear Left Side Door Glass",
        "price": 100.66
      },
      {
        "name": "Crankshaft",
        "price": 4.99
      },
      {
        "name": "Choke cable",
        "price": 130.99
      }
    ],
    "make": "BMW",
    "model": "X6 M",
    "travelledDistance": 483647
  },
  {
    "parts": [
      {
        "name": "Clutch shoe",
        "price": 10.49
      },
      {
        "name": "Thermostat",
        "price": 1050.99
      },
      {
        "name": "Hinge",
        "price": 11.99
      },
      {
        "name": "Rear Right Quarter Glass",
        "price": 100.66
      }
    ],
    "make": "BMW",
    "model": "F04",
    "travelledDistance": 483647
  },
  {
    "parts": [
      {
        "name": "Speed reducer",
        "price": 14.99
      },
      {
        "name": "Valve spring",
        "price": 104.99
      },
      {
        "name": "Oil strainer",
        "price": 45.29
      }
    ],
    "make": "BMW",
    "model": "F20",
    "travelledDistance": 975807
  },
  {
    "parts": [
      {
        "name": "Rims",
        "price": 4020.99
      },
      {
        "name": "Fan belt",
        "price": 10.99
      },
      {
        "name": "Thermostat",
        "price": 1050.99
      },
      {
        "name": "Spoiler",
        "price": 3000.99
      }
    ],
    "make": "BMW",
    "model": "M6 E63",
    "travelledDistance": 214747
  },
  {
    "parts": [
      {
        "name": "Rear Right Side Inner door handle",
        "price": 79.99
      },
      {
        "name": "Front Right Side Inner door handle",
        "price": 100.99
      },
      {
        "name": "Speed reducer",
        "price": 14.99
      },
      {
        "name": "Valve cover",
        "price": 130.99
      }
    ],
    "make": "Fiat",
    "model": "Panda",
    "travelledDistance": 92233854775807
  },
  {
    "parts": [
      {
        "name": "Rear Left Side Inner door handle",
        "price": 93.99
      },
      {
        "name": "Window seal",
        "price": 100.99
      },
      {
        "name": "Clutch assembly",
        "price": 120.99
      },
      {
        "name": "Front Right Side Window motor",
        "price": 44.99
      }
    ],
    "make": "Fiat",
    "model": "Panda 4x4 Antarctica",
    "travelledDistance": 214747
  },
  {
    "parts": [
      {
        "name": "Door control module",
        "price": 421.99
      },
      {
        "name": "Engine block",
        "price": 40.99
      },
      {
        "name": "Oil pipe",
        "price": 100.29
      }
    ],
    "make": "Fiat",
    "model": "500 (2007) Abarth 695 Tributo Maserati",
    "travelledDistance": 214747
  },
  {
    "parts": [
      {
        "name": "Exhaust pipe",
        "price": 130.99
      },
      {
        "name": "Oil pan",
        "price": 140.99
      },
      {
        "name": "Front Left Side Window motor",
        "price": 56.99
      }
    ],
    "make": "Fiat",
    "model": "Panda 4x4 Antarctica",
    "travelledDistance": 2183647
  },
  {
    "parts": [
      {
        "name": "Cowl screen",
        "price": 1500.34
      },
      {
        "name": "Rear Left Side Window motor",
        "price": 144.99
      },
      {
        "name": "Door lock and power door locks",
        "price": 120.99
      },
      {
        "name": "Speed reducer",
        "price": 14.99
      }
    ],
    "make": "Fiat",
    "model": "Panda 4x4",
    "travelledDistance": 2147447
  },
  {
    "parts": [
      {
        "name": "Timing tape",
        "price": 40.90
      },
      {
        "name": "Rear Left Side Outer door handle",
        "price": 120.99
      },
      {
        "name": "Rear Left Quarter Glass",
        "price": 100.55
      },
      {
        "name": "Rocker arm",
        "price": 98.99
      }
    ],
    "make": "Fiat",
    "model": "Panda",
    "travelledDistance": 21447
  },
  {
    "parts": [],
    "make": "Toyota",
    "model": "RAV4",
    "travelledDistance": 33
  }
]
